kmap/__init__.py
kmap/__main__.py
kmap/cli.py
kmap/default_config.toml
kmap/default_motif_def_table.csv
kmap/kmer_count.py
kmap/motif_discovery.py
kmap/taichi_core.py
kmap/util.py
kmap/visualization.py
kmer_map-0.0.7.dist-info/LICENSE
kmer_map-0.0.7.dist-info/METADATA
kmer_map-0.0.7.dist-info/WHEEL
kmer_map-0.0.7.dist-info/entry_points.txt
kmer_map-0.0.7.dist-info/top_level.txt
kmer_map-0.0.7.dist-info/RECORD
