Metadata-Version: 2.1
Name: kmer-map
Version: 0.0.7
Summary: A package for visualizing kmers.
Author-email: "Chengbo Fu, Lu Cheng." <lu.cheng.ac@gmail.com>
License: Apache License
Project-URL: Homepage, https://github.com/chengl7-lab/kmap
Project-URL: Repository, https://github.com/chengl7-lab/kmap.git
Project-URL: Issues, https://github.com/chengl7-lab/kmap/issues
Keywords: kmap,kmer,visualization,dimensionality reduction,DNA,sequences,umap
Classifier: Programming Language :: Python :: 3
Classifier: License :: OSI Approved :: Apache Software License
Classifier: Operating System :: OS Independent
Requires-Python: >=3.11
License-File: LICENSE
Requires-Dist: requests >2
Requires-Dist: scipy >=1.9.3
Requires-Dist: numpy >=1.23.3
Requires-Dist: matplotlib >=3.6.2
Requires-Dist: pandas >=1.5.0
Requires-Dist: click >=8.0.4
Requires-Dist: taichi >=1.5.0
Requires-Dist: biopython >=1.78
Requires-Dist: tomli-w >=1.0.0
Requires-Dist: logomaker >=0.8
Requires-Dist: networkx >=3.3
